shikaku/__init__.py
shikaku/_version.py
shikaku/loader.py
shikaku/py.typed
shikaku/textmodel.py
shikaku/utils.py
shikaku/wordcloud.py
shikaku-0.2.4.dist-info/METADATA
shikaku-0.2.4.dist-info/WHEEL
shikaku-0.2.4.dist-info/licenses/LICENSE
shikaku-0.2.4.dist-info/RECORD
