Metadata-Version: 2.4
Name: shikaku
Version: 0.2.4
Summary: Toolbox for Japanese text.
License: MIT
License-File: LICENSE
Keywords: japanese,text-generation,markov-chain,word-cloud
Author: Takahiro Ueda
Author-email: t.ueda.od@juntendo.ac.jp
Requires-Python: >=3.10,<4.0
Classifier: Development Status :: 4 - Beta
Classifier: License :: OSI Approved :: MIT License
Classifier: Programming Language :: Python :: 3
Classifier: Programming Language :: Python :: 3.10
Classifier: Programming Language :: Python :: 3.11
Classifier: Programming Language :: Python :: 3.12
Classifier: Programming Language :: Python :: 3.13
Classifier: Programming Language :: Python :: 3.14
Classifier: Topic :: Text Processing :: Linguistic
Requires-Dist: igraph (>=0.11.2,<0.12.0)
Requires-Dist: markovify (>=0.9.4,<0.10.0)
Requires-Dist: matplotlib (>=3.7.1,<4.0.0)
Requires-Dist: matplotlib-fontja (>=1.0.0,<2.0.0)
Requires-Dist: mecab-python3 (>=1.0.8,<2.0.0)
Requires-Dist: unidic-lite (>=1.0.8,<2.0.0)
Requires-Dist: wordcloud (>=1.9.2,<2.0.0)
Project-URL: Repository, https://github.com/tueda/shikaku
